noveradb/__init__.py
noveradb/db/__init__.py
noveradb/db/doctor.py
noveradb/db/token.py
noveradb/serializers/__init__.py
noveradb/serializers/base.py
noveradb/serializers/doctor.py
noveradb/serializers/token.py
NoveraDB-0.1.0.dist-info/METADATA
NoveraDB-0.1.0.dist-info/WHEEL
NoveraDB-0.1.0.dist-info/top_level.txt
NoveraDB-0.1.0.dist-info/RECORD
